Workbook
Name SubDomains: 'Tariff and variables'!$D$21:$D$40

Sheet WO Estimation Infosys
A1: WorkOrder Effort specification INFOSYS
A3: Projectcode: | B3: XX9999 | C3: Reviewed by :
A4: Projectname: | B4: (sub-)projectname
A5: PM name: | B5: PM name
A7: Projectscope: | B7: End-2-End
A8: Sub-domain: | B8: <mandatory>
B9: Effort related to Function Points (FP)
B10: Project phase | C10: Development environment | E10: Size (FP) | F10: Effort (Hours)
B12: =IF($E12>0,IF($B$7="DBI / ST","DBI / ST",IF($B$7="End-2-End","End-2-End",IF($B$7="Testing FAT / PPT","Testing",0))),0) -> 0 | C12: Cobol | F12: =IF($E12>0,$E12*'Tariff and variables'!$B8,0) -> 0
C13: Java | F13: =IF($E13>0,$E13*'Tariff and variables'!$B9,0) -> 0
C14: AdvGen Mainframe | F14: =IF($E14>0,$E14*'Tariff and variables'!$B10,0) -> 0
C15: AdvGen Browser | F15: =IF($E15>0,$E15*'Tariff and variables'!$B11,0) -> 0
C16: Peoplesoft | F16: =IF($E16>0,$E16*'Tariff and variables'!$B12,0) -> 0
C17: Internet Banking | F17: =IF($E17>0,$E17*'Tariff and variables'!$B13,0) -> 0
C18: DotNet | F18: =IF($E18>0,$E18*'Tariff and variables'!$B14,0) -> 0
C19: …
C20: … | F20: =E20*14.2 -> 0
C21: A: Sub Totals | E21: =SUM(E12:E20) -> 0 | F21: =SUM($F$12:$F$20) -> 0
B22: Effort not related to Function Points (WBS)
B23: Specification | F23: Effort (Hours)
B33: B: Sub Total | F33: =SUM($F$25:$F$32) -> 0
B34: Effort DBI/ST
B35: Hours A + B | F35: =$F$21+$F$33 -> 0
B36: Effort Post ST
B37: Tariff | F37: Effort (Hours)
B39: =IF('Tariff and variables'!$E$17=28.8%,"28,8% of Effort WBS",IF('Tariff and variables'!$E$17=29.1%,"29,1% of Effort WBS",IF('Tariff and variables'!$E$17=29.4%,"29,4% of Effort WBS","30% of Effort WBS"))) -> #N/A | D39: Included ? | E39: Y | F39: =IF($E$39="Y",IF($B$7="End-2-End",F33*'Tariff and variables'!E17,0),0) -> #N/A
B40: C: Sub Total | F40: =SUM(F39:F39) -> #N/A
B41: Productivity exception
B42: Specification | F42: Effort (Hours)
B49: D: Sub Total | F49: =SUM(F44:F48) -> 0
B50: Total Effort Workorder
B51: Hours A + B + C + D | F51: =ROUND(F35+F40+F49,0) -> #N/A
E52: % Productivity Exception: | F52: =IF(F49>0,ROUND(100*F49/(F35+F40+F49),0),"0") -> 0
E53: % FP: | F53: =IF(F21>0,ROUND(100*(F21+(F21/F35)*F40)/(F35+F40+F49),"0"),"0") -> 0

Sheet Tariff and variables
D2: cobolkorting Usec | F2: 0.25
D4: =LOOKUP('WO Estimation Infosys'!B8,SubDomains,J21:J40) -> #N/A | H4: Start | L4: 1 jaar | P4: 2 jaar | T4: 3 jaar | X4: 4 jaar
B5: Actual | D5: DBI/ST | E5: Testing | F5: E-2-E | H5: DBI/ST | I5: Testing | J5: E-2-E | L5: DBI/ST | M5: Testing | N5: E-2-E | P5: DBI/ST | Q5: Testing | R5: E-2-E | T5: DBI/ST | U5: Testing | V5: E-2-E | X5: DBI/ST | Y5: Testing | Z5: E-2-E
B6: Tariff | D6: Tariff | E6: Tariff | F6: Tariff | H6: Tariff | I6: Tariff | J6: Tariff | L6: Tariff | M6: Tariff | N6: Tariff | P6: Tariff | Q6: Tariff | R6: Tariff | T6: Tariff | U6: Tariff | V6: Tariff | X6: Tariff | Y6: Tariff | Z6: Tariff
B7: (Hours/fp) | D7: (Hours/fp) | E7: (Hours/fp) | F7: (Hours/fp) | H7: (Hours/fp) | I7: (Hours/fp) | J7: (Hours/fp) | L7: (Hours/fp) | M7: (Hours/fp) | N7: (Hours/fp) | P7: (Hours/fp) | Q7: (Hours/fp) | R7: (Hours/fp) | T7: (Hours/fp) | U7: (Hours/fp) | V7: (Hours/fp) | X7: (Hours/fp) | Y7: (Hours/fp) | Z7: (Hours/fp)
B8: =IF('WO Estimation Infosys'!$B$7="DBI / ST",$D8,IF('WO Estimation Infosys'!$B$7="End-2-End",$F8,IF('WO Estimation Infosys'!$B$7="Testing FAT / PPT",$E8,0))) -> #N/A | D8: =IF($D$4=$H$4,$H8,IF($D$4=$L$4,$L8,IF($D$4=$P$4,$P8,IF($D$4=$T$4,$T8,$H8)))) -> #N/A | E8: =IF($D$4=$H$4,$I8,IF($D$4=$L$4,$M8,IF($D$4=$P$4,$Q8,IF($D$4=$T$4,$U8,$I8)))) -> #N/A | F8: =IF($D$4=$H$4,$J8,IF($D$4=$L$4,$N8,IF($D$4=$P$4,$R8,IF($D$4=$T$4,$V8,$J8)))) -> #N/A | H8: 11.16 | I8: 2.98 | J8: 13.18 | L8: 10.83 | M8: 2.92 | N8: 12.78 | P8: 10.61 | Q8: 2.89 | R8: 12.53 | T8: 10.4 | U8: 2.86 | V8: 12.28 | X8: 10.19 | Y8: 2.8 | Z8: 12.03
B9: =IF('WO Estimation Infosys'!$B$7="DBI / ST",$D9,IF('WO Estimation Infosys'!$B$7="End-2-End",$F9,IF('WO Estimation Infosys'!$B$7="Testing FAT / PPT",$E9,0))) -> #N/A | D9: =IF($D$4=$H$4,$H9,IF($D$4=$L$4,$L9,IF($D$4=$P$4,$P9,IF($D$4=$T$4,$T9,$H9)))) -> #N/A | E9: =IF($D$4=$H$4,$I9,IF($D$4=$L$4,$M9,IF($D$4=$P$4,$Q9,IF($D$4=$T$4,$U9,$I9)))) -> #N/A | F9: =IF($D$4=$H$4,$J9,IF($D$4=$L$4,$N9,IF($D$4=$P$4,$R9,IF($D$4=$T$4,$V9,$J9)))) -> #N/A | H9: 9.86 | I9: 2.58 | J9: 11.6 | L9: 9.56 | M9: 2.53 | N9: 11.25 | P9: 9.37 | Q9: 2.5 | R9: 11.03 | T9: 9.18 | U9: 2.48 | V9: 10.81 | X9: 9 | Y9: 2.43 | Z9: 10.59
B10: =IF('WO Estimation Infosys'!$B$7="DBI / ST",$D10,IF('WO Estimation Infosys'!$B$7="End-2-End",$F10,IF('WO Estimation Infosys'!$B$7="Testing FAT / PPT",$E10,0))) -> #N/A | D10: =IF($D$4=$H$4,$H10,IF($D$4=$L$4,$L10,IF($D$4=$P$4,$P10,IF($D$4=$T$4,$T10,$H10)))) -> #N/A | E10: =IF($D$4=$H$4,$I10,IF($D$4=$L$4,$M10,IF($D$4=$P$4,$Q10,IF($D$4=$T$4,$U10,$I10)))) -> #N/A | F10: =IF($D$4=$H$4,$J10,IF($D$4=$L$4,$N10,IF($D$4=$P$4,$R10,IF($D$4=$T$4,$V10,$J10)))) -> #N/A | H10: 0 | I10: 3.8 | J10: 0 | L10: 0 | M10: 3.72 | N10: 0 | P10: 0 | Q10: 3.69 | R10: 0 | T10: 0 | U10: 3.62 | V10: 0 | X10: =T10*0.98 -> 0 | Y10: 3.55 | Z10: =V10*0.98 -> 0
B11: =IF('WO Estimation Infosys'!$B$7="DBI / ST",$D11,IF('WO Estimation Infosys'!$B$7="End-2-End",$F11,IF('WO Estimation Infosys'!$B$7="Testing FAT / PPT",$E11,0))) -> #N/A | D11: =IF($D$4=$H$4,$H11,IF($D$4=$L$4,$L11,IF($D$4=$P$4,$P11,IF($D$4=$T$4,$T11,$H11)))) -> #N/A | E11: =IF($D$4=$H$4,$I11,IF($D$4=$L$4,$M11,IF($D$4=$P$4,$Q11,IF($D$4=$T$4,$U11,$I11)))) -> #N/A | F11: =IF($D$4=$H$4,$J11,IF($D$4=$L$4,$N11,IF($D$4=$P$4,$R11,IF($D$4=$T$4,$V11,$J11)))) -> #N/A | H11: 0 | I11: 3.8 | J11: 0 | L11: 0 | M11: 3.72 | N11: 0 | P11: 0 | Q11: 3.69 | R11: 0 | T11: 0 | U11: 3.65 | V11: 0 | X11: =T11*0.98 -> 0 | Y11: 3.58 | Z11: =V11*0.98 -> 0
B12: =IF('WO Estimation Infosys'!$B$7="DBI / ST",$D12,IF('WO Estimation Infosys'!$B$7="End-2-End",$F12,IF('WO Estimation Infosys'!$B$7="Testing FAT / PPT",$E12,0))) -> #N/A | D12: =IF($D$4=$H$4,$H12,IF($D$4=$L$4,$L12,IF($D$4=$P$4,$P12,IF($D$4=$T$4,$T12,$H12)))) -> #N/A | E12: =IF($D$4=$H$4,$I12,IF($D$4=$L$4,$M12,IF($D$4=$P$4,$Q12,IF($D$4=$T$4,$U12,$I12)))) -> #N/A | F12: =IF($D$4=$H$4,$J12,IF($D$4=$L$4,$N12,IF($D$4=$P$4,$R12,IF($D$4=$T$4,$V12,$J12)))) -> #N/A | H12: 10.3 | I12: 2.98 | J12: 12.16 | L12: 9.99 | M12: 2.92 | N12: 11.8 | P12: 9.79 | Q12: 2.89 | R12: 11.56 | T12: 9.59 | U12: 2.86 | V12: 11.33 | X12: 9.4 | Y12: 2.8 | Z12: 11.1
B13: =IF('WO Estimation Infosys'!$B$7="DBI / ST",$D13,IF('WO Estimation Infosys'!$B$7="End-2-End",$F13,IF('WO Estimation Infosys'!$B$7="Testing FAT / PPT",$E13,0))) -> #N/A | D13: =IF($D$4=$H$4,$H13,IF($D$4=$L$4,$L13,IF($D$4=$P$4,$P13,IF($D$4=$T$4,$T13,$H13)))) -> #N/A | E13: =IF($D$4=$H$4,$I13,IF($D$4=$L$4,$M13,IF($D$4=$P$4,$Q13,IF($D$4=$T$4,$U13,$I13)))) -> #N/A | F13: =IF($D$4=$H$4,$J13,IF($D$4=$L$4,$N13,IF($D$4=$P$4,$R13,IF($D$4=$T$4,$V13,$J13)))) -> #N/A | H13: 16.1 | I13: 5 | J13: 18.9 | L13: 15.62 | M13: 4.9 | N13: 18.33 | P13: 15.3 | Q13: 4.85 | R13: 17.97 | T13: 14.99 | U13: 4.8 | V13: 17.61 | X13: 14.69 | Y13: 4.7 | Z13: 17.26
B14: =IF('WO Estimation Infosys'!$B$7="DBI / ST",$D14,IF('WO Estimation Infosys'!$B$7="End-2-End",$F14,IF('WO Estimation Infosys'!$B$7="Testing FAT / PPT",$E14,0))) -> #N/A | D14: =IF($D$4=$H$4,$H14,IF($D$4=$L$4,$L14,IF($D$4=$P$4,$P14,IF($D$4=$T$4,$T14,$H14)))) -> #N/A | E14: =IF($D$4=$H$4,$I14,IF($D$4=$L$4,$M14,IF($D$4=$P$4,$Q14,IF($D$4=$T$4,$U14,$I14)))) -> #N/A | F14: =IF($D$4=$H$4,$J14,IF($D$4=$L$4,$N14,IF($D$4=$P$4,$R14,IF($D$4=$T$4,$V14,$J14)))) -> #N/A | H14: 8.83 | I14: 1.99 | J14: 10.38 | L14: 8.83 | M14: 1.99 | N14: 10.38 | P14: 8.39 | Q14: 1.93 | R14: 9.87 | T14: 8.22 | U14: 1.91 | V14: 9.67 | X14: 8.06 | Y14: 1.87 | Z14: 9.48
B17: =IF('WO Estimation Infosys'!$B$7="DBI / ST",$D17,IF('WO Estimation Infosys'!$B$7="End-2-End",$F17,IF('WO Estimation Infosys'!$B$7="Testing FAT / PPT",$E17,0))) -> 0 | E17: =IF($D$4=$H$4,$I17,IF($D$4=$L$4,$M17,IF($D$4=$P$4,$Q17,IF($D$4=$T$4,$U17,$I17)))) -> #N/A | I17: 0.3 | M17: 0.294 | Q17: 0.291 | U17: 0.288 | Y17: 0.285
D20: SUBDOMAIN | I20: startdate | J20: cijfers
D21: Accounts, Savings & Customers | J21: start
D22: ALM, Cost Accounting & Controlling | J22: start
D23: Cash & Cards | J23: start
D24: Credits | I24: 40909 | J24: 4 jaar
D25: Data Warehouse (ADW) | J25: start
D26: Document Services & Archiving | I26: 40756 | J26: 4 jaar
D27: Finance | J27: start
D28: FX&R & Cross Markets Services | I28: oct-15 | J28: start
D29: Insurance & Generic Tariffs | J29: start
D30: Mortgages & BI | J30: start
D31: OCRM & Advice | J31: start
D32: Payments | I32: 40848 | J32: 4 jaar
D33: PRI&TOPS | I33: 40817 | J33: 4 jaar
D34: Risk | J34: start
D35: Sales & Services | J35: start
D36: Securities | J36: start
D37: Securities Financing & Equities | J37: start
D38: Trade & Guarentees | I38: 41000 | J38: 3 jaar
D39: Transactions & Content | J39: start
D40: User Security | I40: 41122 | J40: 3 jaar
